LICENSE
MANIFEST.in
README.md
setup.py
url_regex/__init__.py
url_regex/tlds.py
url_regex/url_regex.py
url_regex.egg-info/PKG-INFO
url_regex.egg-info/SOURCES.txt
url_regex.egg-info/dependency_links.txt
url_regex.egg-info/top_level.txt