Metadata-Version: 1.1
Name: url-regex
Version: 1.0.3
Summary: Regular expression for matching URLs in Python
Home-page: https://github.com/AlexFlipnote/url_regex
Author: AlexFlipnote
Author-email: UNKNOWN
License: GPLv3
Platform: UNKNOWN
Classifier: License :: OSI Approved :: GNU General Public License v3 (GPLv3)
Classifier: Programming Language :: Python :: 3.6
Classifier: Programming Language :: Python :: 3.7
